mcts.py
mcts-1.0.4.dist-info/LICENSE.txt
mcts-1.0.4.dist-info/METADATA
mcts-1.0.4.dist-info/WHEEL
mcts-1.0.4.dist-info/top_level.txt
mcts-1.0.4.dist-info/RECORD
