Metadata-Version: 2.1
Name: mcts
Version: 1.0.4
Summary: A simple package to allow users to run Monte Carlo Tree Search on any perfect information domain
Home-page: https://github.com/pbsinclair42/MCTS
Author: Paul Sinclair
Author-email: pbsinclair42@gmail.com
License: MIT
Keywords: mcts,monte,carlo,tree,search
Platform: UNKNOWN
Classifier: Development Status :: 4 - Beta
Classifier: Intended Audience :: Developers
Classifier: Intended Audience :: Education
Classifier: Intended Audience :: Science/Research
Classifier: License :: OSI Approved :: MIT License
Classifier: Operating System :: OS Independent
Classifier: Programming Language :: Python :: 2
Classifier: Programming Language :: Python :: 3
Classifier: Topic :: Scientific/Engineering
Classifier: Topic :: Scientific/Engineering :: Artificial Intelligence
Classifier: Topic :: Software Development
Classifier: Topic :: Software Development :: Libraries
Classifier: Topic :: Software Development :: Libraries :: Python Modules
